Costa/__init__.py
CostaOS-0.0.2.dist-info/METADATA
CostaOS-0.0.2.dist-info/WHEEL
CostaOS-0.0.2.dist-info/top_level.txt
CostaOS-0.0.2.dist-info/RECORD
